datreant/__init__.py
datreant/collections.py
datreant/exceptions.py
datreant/manipulators.py
datreant/metadata.py
datreant/names.py
datreant/rsync.py
datreant/selectionparser.py
datreant/state.py
datreant/treants.py
datreant/trees.py
datreant/util.py
datreant/core/__init__.py
datreant/scripts/__init__.py
datreant/scripts/datreant_07to1.py
datreant/tests/__init__.py
datreant/tests/test_collections.py
datreant/tests/test_locks.py
datreant/tests/test_manipulators.py
datreant/tests/test_parser.py
datreant/tests/test_rsync.py
datreant/tests/test_treants.py
datreant/tests/test_trees.py
datreant/tests/test_util.py
datreant-1.1.1.dist-info/AUTHORS
datreant-1.1.1.dist-info/LICENSE
datreant-1.1.1.dist-info/METADATA
datreant-1.1.1.dist-info/WHEEL
datreant-1.1.1.dist-info/entry_points.txt
datreant-1.1.1.dist-info/top_level.txt
datreant-1.1.1.dist-info/RECORD
