Metadata-Version: 2.1
Name: datreant
Version: 1.1.1
Summary: persistent, pythonic trees for heterogeneous data
Home-page: http://datreant.org/
Author: David Dotson
Author-email: dotsdl@gmail.com
License: BSD
Platform: UNKNOWN
Classifier: Development Status :: 4 - Beta
Classifier: Environment :: Console
Classifier: Intended Audience :: Science/Research
Classifier: License :: OSI Approved :: BSD License
Classifier: Operating System :: POSIX
Classifier: Programming Language :: Python
Classifier: Topic :: Scientific/Engineering
Classifier: Topic :: Software Development :: Libraries :: Python Modules
License-File: LICENSE
License-File: AUTHORS
Requires-Dist: asciitree
Requires-Dist: scandir
Requires-Dist: fuzzywuzzy
Requires-Dist: python-Levenshtein
Requires-Dist: pyparsing (>=3.0)
